ueosio/__init__.py
ueosio/abi.py
ueosio/ds.py
ueosio/rpc.py
ueosio/utils.py
ueosio-0.2.5.dist-info/LICENSE
ueosio-0.2.5.dist-info/WHEEL
ueosio-0.2.5.dist-info/METADATA
ueosio-0.2.5.dist-info/RECORD
