Metadata-Version: 2.1
Name: ueosio
Version: 0.2.5
Summary: uEOSIO python library
Home-page: https://github.com/EOSArgentina/ueosio
Author: Matias Romeo
Author-email: matias.romeo@gmail.com
Requires-Python: >=3.6,<4.0
Classifier: Programming Language :: Python :: 3
Classifier: Programming Language :: Python :: 3.6
Classifier: Programming Language :: Python :: 3.7
Classifier: Programming Language :: Python :: 3.8
Classifier: Programming Language :: Python :: 3.9
Requires-Dist: base58 (>=2.0.0,<3.0.0)
Requires-Dist: cryptos (>=1.36,<2.0)
Requires-Dist: requests (>=2.23.0,<3.0.0)
Project-URL: Repository, https://github.com/EOSArgentina/ueosio
